AUTHORS
CHANGELOG.txt
DESCRIPTION
LICENSE
MANIFEST.in
README.rst
setup.py
django_subscribe.egg-info/PKG-INFO
django_subscribe.egg-info/SOURCES.txt
django_subscribe.egg-info/dependency_links.txt
django_subscribe.egg-info/requires.txt
django_subscribe.egg-info/top_level.txt
subscribe/__init__.py
subscribe/admin.py
subscribe/forms.py
subscribe/models.py
subscribe/urls.py
subscribe/views.py
subscribe/migrations/0001_initial.py
subscribe/migrations/__init__.py
subscribe/south_migrations/0001_initial.py
subscribe/south_migrations/0002_auto__add_unique_subscription_user_content_type_object_id.py
subscribe/south_migrations/__init__.py
subscribe/templates/subscribe/subscription_delete.html
subscribe/templates/subscribe/subscription_form.html
subscribe/templatetags/__init__.py
subscribe/templatetags/subscribe_tags.py
subscribe/tests/__init__.py
subscribe/tests/forms_tests.py
subscribe/tests/models_tests.py
subscribe/tests/settings.py
subscribe/tests/subscribe_tags_tests.py
subscribe/tests/test_settings.py
subscribe/tests/urls.py
subscribe/tests/views_tests.py
subscribe/tests/test_app/__init__.py
subscribe/tests/test_app/models.py
subscribe/tests/test_app/templates/base.html
subscribe/tests/test_app/templates/registration/login.html