Metadata-Version: 1.0
Name: django-subscribe
Version: 0.1.5
Summary: A simple subscription app for Django. Allows a user to subscribe to any object.
